[
  {
    "name": "David",
    "nickname": "Dav082004",
    "github": "https://github.com/Dav082004",
    "linkedin": "https://www.linkedin.com/in/davidcontreraspalacios",
    "instagram": "https://www.instagram.com/davidc_8n/",
    "image": "https://github.com/Dav082004.png",
    "description": "Apasionado por la tecnología y la enseñanza. Me encanta crear proyectos que ayuden a otros a aprender.",
    "hobbies": [
      "Programación",
      "Open Source",
      "Github",
      "Gaming"
    ]
  },
  {
    "name": "Luzylay",
    "nickname": "Luzylay",
    "github": "https://github.com/luzylay",
    "image": "https://github.com/luzylay.png",
    "description": "Me gusta arreglar cosasxd ",
    "hobbies": [
      "Cyber",
      "Open Source",
      "Github",
      "IoT"
    ]
  },
  {
    "name": "OctocatChambeador",
    "nickname": "xde268106-lab",
    "github": "https://github.com/xde268106-lab",
    "linkedin": "https://www.linkedin.com/in/-",
    "instagram": "https://www.instagram.com/-",
    "image": "https://github.com/xde268106-lab.png",
    "description": "Me gusta arreglar cosas.",
    "hobbies": [
      "Cyber",
      "Open Source",
      "Github",
      "IoT"
    ]
  }
]